raquel/__init__.py
raquel/core/__init__.py
raquel/core/base.py
raquel/core/common.py
raquel/core/core_async.py
raquel/core/core_sync.py
raquel/models/__init__.py
raquel/models/base_job.py
raquel/models/base_sql.py
raquel/models/job.py
raquel/models/params.py
raquel/models/queue_stats.py
raquel/models/raw_job.py
raquel-0.3.2.dist-info/METADATA
raquel-0.3.2.dist-info/WHEEL
raquel-0.3.2.dist-info/licenses/LICENSE
raquel-0.3.2.dist-info/RECORD
