Metadata-Version: 2.4
Name: raquel
Version: 0.3.2
Summary: Simple Job Queues using SQL
Project-URL: Homepage, https://github.com/vduseev/raquel
Project-URL: Repository, https://github.com/vduseev/raquel
Author-email: vduseev <vagiz@duseev.com>
License-Expression: Apache-2.0
License-File: LICENSE
Keywords: distributed,job,queue,sql,task,worker
Classifier: Development Status :: 5 - Production/Stable
Classifier: Intended Audience :: Developers
Classifier: License :: OSI Approved :: Apache Software License
Classifier: Programming Language :: Python :: 3
Classifier: Programming Language :: Python :: 3.10
Classifier: Programming Language :: Python :: 3.11
Classifier: Programming Language :: Python :: 3.12
Classifier: Programming Language :: Python :: 3.13
Classifier: Programming Language :: Python :: 3.14
Classifier: Topic :: Software Development :: Libraries
Classifier: Topic :: System :: Distributed Computing
Requires-Python: ~=3.10
Requires-Dist: sqlalchemy~=2.0
Provides-Extra: asyncio
Requires-Dist: greenlet~=3.0; extra == 'asyncio'
